pyuu/signed_set/__init__.py
pyuu/signed_set/signed_set.py
pyuu.signed_set-0.0.0.dist-info/METADATA
pyuu.signed_set-0.0.0.dist-info/WHEEL
pyuu.signed_set-0.0.0.dist-info/top_level.txt
pyuu.signed_set-0.0.0.dist-info/RECORD
